README.rst
redis_writer.py
setup.py
redis_writer.egg-info/PKG-INFO
redis_writer.egg-info/SOURCES.txt
redis_writer.egg-info/dependency_links.txt
redis_writer.egg-info/not-zip-safe
redis_writer.egg-info/requires.txt
redis_writer.egg-info/top_level.txt